dry_pyutils/__init__.py
dry_pyutils/constants.py
dry_pyutils/transformation.py
dry_pyutils/validation.py
dry_pyutils/wrappers.py
DRY_python_utilities-1.0.0.dist-info/LICENSE
DRY_python_utilities-1.0.0.dist-info/METADATA
DRY_python_utilities-1.0.0.dist-info/WHEEL
DRY_python_utilities-1.0.0.dist-info/top_level.txt
DRY_python_utilities-1.0.0.dist-info/RECORD
