Metadata-Version: 2.1
Name: DRY-python-utilities
Version: 1.0.0
Summary: A set of python utilities
Home-page: https://github.com/monthero/dry-pyutils
Author: Vasco Monteiro
Author-email: vmnokk@gmail.com
License: MIT
Project-URL: Changelog, https://github.com/monthero/dry-pyutils/blob/master/CHANGELOG.md
Project-URL: Instructions, https://github.com/monthero/dry-pyutils/blob/master/README.md
Platform: UNKNOWN
Classifier: Development Status :: 4 - Beta
Classifier: Operating System :: OS Independent
Classifier: Intended Audience :: Developers
Classifier: License :: OSI Approved :: MIT License
Classifier: Operating System :: OS Independent
Classifier: Programming Language :: Python
Classifier: Programming Language :: Python :: 3.5
Classifier: Programming Language :: Python :: 3.6
Classifier: Programming Language :: Python :: 3.7
Classifier: Programming Language :: Python :: 3.8
Classifier: Programming Language :: Python :: 3.9
Classifier: Programming Language :: Python :: 3 :: Only
Classifier: Topic :: Software Development :: Libraries :: Python Modules
Requires-Python: >=3.5.0
Requires-Dist: python-slugify
Requires-Dist: bleach
